coollearn/__init__.py
coollearn/common.py
coollearn/coollearn.png
coollearn/coollearn.py
coollearn-0.1.10.dist-info/METADATA
coollearn-0.1.10.dist-info/WHEEL
coollearn-0.1.10.dist-info/entry_points.txt
coollearn-0.1.10.dist-info/top_level.txt
coollearn-0.1.10.dist-info/RECORD
