Metadata-Version: 2.1
Name: coollearn
Version: 0.1.10
Summary: Personalized Learning Assistant
Author: boyjiangboyu
Author-email: boyjiangboyu@outlook.com
Classifier: Programming Language :: Python :: 3
Classifier: License :: OSI Approved :: MIT License
Classifier: Operating System :: OS Independent
Requires-Python: >=3.10
Requires-Dist: zhipuai (>=2.0.1)
Requires-Dist: streamlit (>=1.31.1)
Requires-Dist: python-dotenv (>=1.0.1)
